mbed_targets/__init__.py
mbed_targets/_version.py
mbed_targets/board.py
mbed_targets/boards.py
mbed_targets/env.py
mbed_targets/exceptions.py
mbed_targets/get_board.py
mbed_targets/get_target.py
mbed_targets/mbed_tools.py
mbed_targets/target.py
mbed_targets/_internal/__init__.py
mbed_targets/_internal/board_database.py
mbed_targets/_internal/exceptions.py
mbed_targets/_internal/target_attributes.py
mbed_targets/_internal/data/board_database_snapshot.json
mbed_targets/_internal/data/targets_metadata.json
mbed_targets/_internal/targets_json_parsers/__init__.py
mbed_targets/_internal/targets_json_parsers/accumulating_attribute_parser.py
mbed_targets/_internal/targets_json_parsers/overriding_attribute_parser.py
mbed_targets-1.1.1.dist-info/LICENSE
mbed_targets-1.1.1.dist-info/METADATA
mbed_targets-1.1.1.dist-info/WHEEL
mbed_targets-1.1.1.dist-info/top_level.txt
mbed_targets-1.1.1.dist-info/RECORD
