Metadata-Version: 2.1
Name: mbed-targets
Version: 1.1.1
Summary: Target Abstraction for Mbed OS
Home-page: https://github.com/ARMmbed/mbed-targets
Author: Mbed team
Author-email: support@mbed.com
License: Apache 2.0
Keywords: Arm Mbed OS MbedOS build target platform board module
Platform: UNKNOWN
Classifier: Development Status :: 3 - Alpha
Classifier: Intended Audience :: Developers
Classifier: License :: OSI Approved :: Apache Software License
Classifier: Programming Language :: Python
Classifier: Programming Language :: Python :: 3 :: Only
Classifier: Programming Language :: Python :: 3.6
Classifier: Programming Language :: Python :: 3.7
Classifier: Programming Language :: Python :: 3.8
Classifier: Topic :: Software Development :: Build Tools
Classifier: Topic :: Software Development :: Embedded Systems
Requires-Python: >=3.6,<4
Requires-Dist: requests (>=2.20)
Requires-Dist: python-dotenv
Requires-Dist: mbed-tools-lib (~=1.2)
Requires-Dist: pdoc3
Requires-Dist: mbed-project (~=2.0)
Requires-Dist: dataclasses ; python_version < "3.7"
